classification_model/VERSION
classification_model/__init__.py
classification_model/config.yml
classification_model/pipeline.py
classification_model/predict.py
classification_model/train_pipeline.py
classification_model/config/__init__.py
classification_model/config/core.py
classification_model/datasets/__init__.py
classification_model/datasets/test.csv
classification_model/processing/__init__.py
classification_model/processing/data_manager.py
classification_model/processing/features.py
classification_model/processing/validation.py
classification_model/trained_models/__init__.py
classification_model/trained_models/titanic_model_output_v0.0.20.pkl
survival_titanic-0.0.20.dist-info/METADATA
survival_titanic-0.0.20.dist-info/WHEEL
survival_titanic-0.0.20.dist-info/top_level.txt
survival_titanic-0.0.20.dist-info/RECORD
